{
    "available_space": false,
    "files": [
        {
            "name": "The Human League - Don't You Want Me (Official Music Video)-uPudE8nDog0.mp4",
            "path": "music_x1/videos/The Human League - Don't You Want Me (Official Music Video)-uPudE8nDog0.mp4",
            "size": 10.842315776000001
        },
        {
            "name": "Control Machete - Danzón-_YeFm_hCtxY.mp4",
            "path": "music_x1/videos/Control Machete - Danzón-_YeFm_hCtxY.mp4",
            "size": 14.726528
        },
        {
            "name": "Ska-P - Consumo Gusto-kbXWUE6GdQc.mp4",
            "path": "music_x1/videos/Ska-P - Consumo Gusto-kbXWUE6GdQc.mp4",
            "size": 7.043169280000001
        },
        {
            "name": "Prenda querida - cadetes de linares-VOstTdFYsGU.mp4",
            "path": "music_x1/videos/Prenda querida - cadetes de linares-VOstTdFYsGU.mp4",
            "size": 19.676051456
        },
        {
            "name": "Toto - Rosanna (Official Music Video)-qmOLtTGvsbM.mp4",
            "path": "music_x1/videos/Toto - Rosanna (Official Music Video)-qmOLtTGvsbM.mp4",
            "size": 24.191550464000002
        },
        {
            "name": "Tchaikovsky - Marche Slave-5poSw7tFLB4.mp4",
            "path": "music_x1/videos/Tchaikovsky - Marche Slave-5poSw7tFLB4.mp4",
            "size": 10.135766016
        },
        {
            "name": "Los Cadetes de Linares - De Ramones a Los Algodones-WVfNy0gjk4M.mp4",
            "path": "music_x1/videos/Los Cadetes de Linares - De Ramones a Los Algodones-WVfNy0gjk4M.mp4",
            "size": 5.827702784
        },
        {
            "name": "Don Osvaldo -Bienvenidos- en vivo en Plaza de la música [Video oficial]-6VFQeWME-0E.mp4",
            "path": "music_x1/videos/Don Osvaldo -Bienvenidos- en vivo en Plaza de la música [Video oficial]-6VFQeWME-0E.mp4",
            "size": 16.482397184
        },
        {
            "name": "Los Cadetes de Linares - El Unico Camino-aJEJbyy70L4.mp4",
            "path": "music_x1/videos/Los Cadetes de Linares - El Unico Camino-aJEJbyy70L4.mp4",
            "size": 4.112234496
        },
        {
            "name": "Chuy vega  Me Desperto La Realidad-pFB5ZEP8O_M.mp4",
            "path": "music_x1/videos/Chuy vega  Me Desperto La Realidad-pFB5ZEP8O_M.mp4",
            "size": 3.4708357120000004
        },
        {
            "name": "Los Cadetes de Linares - Tu Buen Camino---aGfsdoMv8.mp4",
            "path": "music_x1/videos/Los Cadetes de Linares - Tu Buen Camino---aGfsdoMv8.mp4",
            "size": 3.378550784
        },
        {
            "name": "Conjunto Primavera - Morir De Amor-4RSBHZxserY.mp4",
            "path": "music_x1/videos/Conjunto Primavera - Morir De Amor-4RSBHZxserY.mp4",
            "size": 13.789604864000001
        },
        {
            "name": "Los Invasores Avientame-WNnKTEYRw5g.mp4",
            "path": "music_x1/videos/Los Invasores Avientame-WNnKTEYRw5g.mp4",
            "size": 4.607874048
        },
        {
            "name": "The Residents - Breath and Length-gWamTZgk1aQ.mp4",
            "path": "music_x1/videos/The Residents - Breath and Length-gWamTZgk1aQ.mp4",
            "size": 2.551617536
        },
        {
            "name": "DragonForce - Through the Fire and Flames (Official Video)-0jgrCKhxE1s.mp4",
            "path": "music_x1/videos/DragonForce - Through the Fire and Flames (Official Video)-0jgrCKhxE1s.mp4",
            "size": 19.154762752
        },
        {
            "name": "Calle 13 - Que Lloren (Audio)-KTs-LhwiF8Y.mp4",
            "path": "music_x1/videos/Calle 13 - Que Lloren (Audio)-KTs-LhwiF8Y.mp4",
            "size": 8.759949312
        },
        {
            "name": "Little Richard - Rip It Up-pc_F3PaYgl0.mp4",
            "path": "music_x1/videos/Little Richard - Rip It Up-pc_F3PaYgl0.mp4",
            "size": 4.409120768
        },
        {
            "name": "Muse - Can't Take My Eyes Off You-jMeBAltloqo.mp4",
            "path": "music_x1/videos/Muse - Can't Take My Eyes Off You-jMeBAltloqo.mp4",
            "size": 6.0656814080000006
        },
        {
            "name": "CARL BUTLER -   JEALOUS HEART-copsmkLRBd4.mp4",
            "path": "music_x1/videos/CARL BUTLER -   JEALOUS HEART-copsmkLRBd4.mp4",
            "size": 10.970891264
        },
        {
            "name": "Carlos Vega Rosa Linda--MHWYQ2rqGo.mp4",
            "path": "music_x1/videos/Carlos Vega Rosa Linda--MHWYQ2rqGo.mp4",
            "size": 4.861601792
        },
        {
            "name": "Las Ketchup - The Ketchup Song (Asereje) (Spanglish Version) (Official Video)-AMT698ArSfQ.mp4",
            "path": "music_x1/videos/Las Ketchup - The Ketchup Song (Asereje) (Spanglish Version) (Official Video)-AMT698ArSfQ.mp4",
            "size": 19.91117312
        },
        {
            "name": "Eskorbuto - Felices dias de tu vida-X9wwg60O2OQ.mp4",
            "path": "music_x1/videos/Eskorbuto - Felices dias de tu vida-X9wwg60O2OQ.mp4",
            "size": 4.065238016
        },
        {
            "name": "Los Muertos de Cristo - El ángel de la muerte-c10Dd2AOeH8.mp4",
            "path": "music_x1/videos/Los Muertos de Cristo - El ángel de la muerte-c10Dd2AOeH8.mp4",
            "size": 7.0256476160000005
        },
        {
            "name": "Liam Payne, Rita Ora - For You (Fifty Shades Freed) (Official Music Video)-RQUuqbzQVsY.mp4",
            "path": "music_x1/videos/Liam Payne, Rita Ora - For You (Fifty Shades Freed) (Official Music Video)-RQUuqbzQVsY.mp4",
            "size": 14.855036928
        },
        {
            "name": "CONJUNTO PRIMAVERA ,CON NACHO PA QUE SON PASIONES-Rl709UpBY4k.mp4",
            "path": "music_x1/videos/CONJUNTO PRIMAVERA ,CON NACHO PA QUE SON PASIONES-Rl709UpBY4k.mp4",
            "size": 7.824265216000001
        },
        {
            "name": "La Muerte Del Torito (En Vivo)-LbPph6Hmai4.mp4",
            "path": "music_x1/videos/La Muerte Del Torito (En Vivo)-LbPph6Hmai4.mp4",
            "size": 12.279122944000001
        },
        {
            "name": "Ladykiller-t15QtuiLGmI.mp4",
            "path": "music_x1/videos/Ladykiller-t15QtuiLGmI.mp4",
            "size": 7.4165329920000005
        },
        {
            "name": "Creedence Clearwater Revival - Fortunate Son-ZWijx_AgPiA.mp4",
            "path": "music_x1/videos/Creedence Clearwater Revival - Fortunate Son-ZWijx_AgPiA.mp4",
            "size": 11.107761152
        },
        {
            "name": "Shakira - Que Me Quedes Tu (Video Oficial)-WlSBl0YUZcc.mp4",
            "path": "music_x1/videos/Shakira - Que Me Quedes Tu (Video Oficial)-WlSBl0YUZcc.mp4",
            "size": 19.834722304
        },
        {
            "name": "Lish & Mr.What - Experimental Movement-idjKfPWurn0.mp4",
            "path": "music_x1/videos/Lish & Mr.What - Experimental Movement-idjKfPWurn0.mp4",
            "size": 13.045080064
        },
        {
            "name": "LOS CADETES  DE LINARES   EN TU DIA-CgluoEBOtbc.mp4",
            "path": "music_x1/videos/LOS CADETES  DE LINARES   EN TU DIA-CgluoEBOtbc.mp4",
            "size": 4.45367808
        },
        {
            "name": "Emperor - An Elegy Of Icaros-JMs2rgj70GM.mp4",
            "path": "music_x1/videos/Emperor - An Elegy Of Icaros-JMs2rgj70GM.mp4",
            "size": 13.169011712000001
        },
        {
            "name": "Sentimental-UmMXXrlcc_c.mp4",
            "path": "music_x1/videos/Sentimental-UmMXXrlcc_c.mp4",
            "size": 7.281974272
        },
        {
            "name": "Europe - Farewell-rPa6VdKC8Po.mp4",
            "path": "music_x1/videos/Europe - Farewell-rPa6VdKC8Po.mp4",
            "size": 8.150506496
        },
        {
            "name": "Thin Lizzy - Whiskey In The Jar (official music video)-wyQ-tScuzwM.mp4",
            "path": "music_x1/videos/Thin Lizzy - Whiskey In The Jar (official music video)-wyQ-tScuzwM.mp4",
            "size": 16.804000768
        },
        {
            "name": "Conjunto Primavera Dos Caminos-SWQhLbKRVu4.mp4",
            "path": "music_x1/videos/Conjunto Primavera Dos Caminos-SWQhLbKRVu4.mp4",
            "size": 6.593258496000001
        },
        {
            "name": "Papalote - Silvio Rodríguez-a8o-FJ_N41Y.mp4",
            "path": "music_x1/videos/Papalote - Silvio Rodríguez-a8o-FJ_N41Y.mp4",
            "size": 9.735673856
        },
        {
            "name": "Eskorbuto- Salvelo-eV5_koLUvXM.mp4",
            "path": "music_x1/videos/Eskorbuto- Salvelo-eV5_koLUvXM.mp4",
            "size": 4.513002496
        },
        {
            "name": "Transmetal - Ceveline (audio oficial)--YwxKgOgL-4.mp4",
            "path": "music_x1/videos/Transmetal - Ceveline (audio oficial)--YwxKgOgL-4.mp4",
            "size": 9.159468032000001
        },
        {
            "name": "Conjunto Primavera 'Mirame De Frente'-LcfZ52455vQ.mp4",
            "path": "music_x1/videos/Conjunto Primavera 'Mirame De Frente'-LcfZ52455vQ.mp4",
            "size": 7.8433566720000005
        },
        {
            "name": "Stevie Ray Vaughan & Double Trouble - Riviera Paradise (Live From Austin, TX)-3c_8VUL5jks.mp4",
            "path": "music_x1/videos/Stevie Ray Vaughan & Double Trouble - Riviera Paradise (Live From Austin, TX)-3c_8VUL5jks.mp4",
            "size": 38.100114432000005
        },
        {
            "name": "The Changing Of Times-OJmVORu1bSo.mp4",
            "path": "music_x1/videos/The Changing Of Times-OJmVORu1bSo.mp4",
            "size": 6.646885376
        },
        {
            "name": "Te busco en todas partes-MdDSvSklOUU.mp4",
            "path": "music_x1/videos/Te busco en todas partes-MdDSvSklOUU.mp4",
            "size": 4.452118528000001
        },
        {
            "name": "Letting Go Of Tonight-F7aP3NJGuNw.mp4",
            "path": "music_x1/videos/Letting Go Of Tonight-F7aP3NJGuNw.mp4",
            "size": 3.040411648
        },
        {
            "name": "La Vieja Banca-z-wJMbX2QrY.mp4",
            "path": "music_x1/videos/La Vieja Banca-z-wJMbX2QrY.mp4",
            "size": 6.638410752
        },
        {
            "name": "Hypnolove - La piscine (Official Audio)-iNvye72Cpx0.mp4",
            "path": "music_x1/videos/Hypnolove - La piscine (Official Audio)-iNvye72Cpx0.mp4",
            "size": 5.298625536
        },
        {
            "name": "Mephisto-RjwzeOCD0s0.mp4",
            "path": "music_x1/videos/Mephisto-RjwzeOCD0s0.mp4",
            "size": 10.903407616
        },
        {
            "name": "Muse - Starlight [Official Music Video]-Pgum6OT_VH8.mp4",
            "path": "music_x1/videos/Muse - Starlight [Official Music Video]-Pgum6OT_VH8.mp4",
            "size": 16.99575296
        },
        {
            "name": "Conjunto Primavera - Sentí (Animated Video)-OOuawaUiX8c.mp4",
            "path": "music_x1/videos/Conjunto Primavera - Sentí (Animated Video)-OOuawaUiX8c.mp4",
            "size": 11.615890432
        },
        {
            "name": "Ceaese, Polima Westcoast, Young Cister - Te Quiero Ver-kWleUVZNws8.mp4",
            "path": "music_x1/videos/Ceaese, Polima Westcoast, Young Cister - Te Quiero Ver-kWleUVZNws8.mp4",
            "size": 3.5597588480000004
        },
        {
            "name": "pesado ' Jamas Regresaras '-PRcjv-IJD7s.mp4",
            "path": "music_x1/videos/pesado ' Jamas Regresaras '-PRcjv-IJD7s.mp4",
            "size": 10.389321728
        },
        {
            "name": "Come Home- One Republic feat. Sara Bareilles-69czQMuwwp4.mp4",
            "path": "music_x1/videos/Come Home- One Republic feat. Sara Bareilles-69czQMuwwp4.mp4",
            "size": 6.507295744
        },
        {
            "name": "System Of A Down - Toxicity (Official Video)-iywaBOMvYLI.mp4",
            "path": "music_x1/videos/System Of A Down - Toxicity (Official Video)-iywaBOMvYLI.mp4",
            "size": 18.74130432
        },
        {
            "name": "Estigia - El Punk es contracultura (Disco completo)-IlEZlo5uWfc.mp4",
            "path": "music_x1/videos/Estigia - El Punk es contracultura (Disco completo)-IlEZlo5uWfc.mp4",
            "size": 26.273506304
        },
        {
            "name": "Plastic Passion-b3UlHQsfecY.mp4",
            "path": "music_x1/videos/Plastic Passion-b3UlHQsfecY.mp4",
            "size": 2.9354137600000003
        },
        {
            "name": "Pesado, Lorenzo de Monteclaro - Abrazado De Un Poste-mvBiuV3i9N8.mp4",
            "path": "music_x1/videos/Pesado, Lorenzo de Monteclaro - Abrazado De Un Poste-mvBiuV3i9N8.mp4",
            "size": 16.092886016
        },
        {
            "name": "Silver-sQ_QRK_iWrk.mp4",
            "path": "music_x1/videos/Silver-sQ_QRK_iWrk.mp4",
            "size": 6.8166912
        },
        {
            "name": "Lil Rob - Summer Time (NEW 2010) Oldie Collection-ps3vZqRGkvY.mp4",
            "path": "music_x1/videos/Lil Rob - Summer Time (NEW 2010) Oldie Collection-ps3vZqRGkvY.mp4",
            "size": 8.538677248
        },
        {
            "name": "Jan Johansson - Polska från Medelpad (Official Audio)-KY6IBaDCd3U.mp4",
            "path": "music_x1/videos/Jan Johansson - Polska från Medelpad (Official Audio)-KY6IBaDCd3U.mp4",
            "size": 4.131827712000001
        },
        {
            "name": "03. Lasser & Cráneo - Bahía _ Prod. Made in M & Juan RIOS-TQrBGUkRhjs.mp4",
            "path": "music_x1/videos/03. Lasser & Cráneo - Bahía _ Prod. Made in M & Juan RIOS-TQrBGUkRhjs.mp4",
            "size": 12.400466944000001
        },
        {
            "name": "Creedence Clearwater Revival - Before You Accuse Me-wLCacbZxuc4.mp4",
            "path": "music_x1/videos/Creedence Clearwater Revival - Before You Accuse Me-wLCacbZxuc4.mp4",
            "size": 6.350398464
        },
        {
            "name": "Stevie Ray Vaughan - Life Without You - 9_21_1985 - Capitol Theatre, Passaic, NJ-DQ4REYdCkTw.mp4",
            "path": "music_x1/videos/Stevie Ray Vaughan - Life Without You - 9_21_1985 - Capitol Theatre, Passaic, NJ-DQ4REYdCkTw.mp4",
            "size": 49.966340096
        },
        {
            "name": "Speak My Language-JI9ZfDagOPQ.mp4",
            "path": "music_x1/videos/Speak My Language-JI9ZfDagOPQ.mp4",
            "size": 3.545032704
        },
        {
            "name": "Calle 13 - Cumbia de los Aburridos (Video)-if5vMPDxxEE.mp4",
            "path": "music_x1/videos/Calle 13 - Cumbia de los Aburridos (Video)-if5vMPDxxEE.mp4",
            "size": 23.862742016000002
        },
        {
            "name": "Prime VGM 156 - Dragon Force - Snow Land (Extended)-G5vN7c2K6og.mp4",
            "path": "music_x1/videos/Prime VGM 156 - Dragon Force - Snow Land (Extended)-G5vN7c2K6og.mp4",
            "size": 41.162048512000005
        },
        {
            "name": "CARL HENRY ♦ Into My Life + Version {STUDIO 1 BLANK 7inch}-b1fOfROg8uk.mp4",
            "path": "music_x1/videos/CARL HENRY ♦ Into My Life + Version {STUDIO 1 BLANK 7inch}-b1fOfROg8uk.mp4",
            "size": 6.592914432000001
        },
        {
            "name": "The Shadows - Johnny Guitar-rxJ1jaWsVYU.mp4",
            "path": "music_x1/videos/The Shadows - Johnny Guitar-rxJ1jaWsVYU.mp4",
            "size": 9.215669248000001
        },
        {
            "name": "Piero - Caminando por Caracas [Canción Oficial] ®-fF7pc3oyzDs.mp4",
            "path": "music_x1/videos/Piero - Caminando por Caracas [Canción Oficial] ®-fF7pc3oyzDs.mp4",
            "size": 4.247647232
        },
        {
            "name": "Calle 13 - Un Beso de Desayuno (Video)-6vKE1Ix6BPQ.mp4",
            "path": "music_x1/videos/Calle 13 - Un Beso de Desayuno (Video)-6vKE1Ix6BPQ.mp4",
            "size": 23.107575808
        },
        {
            "name": "The Tear Of The Year ~ Jackie Wilson (1960)-ESX5rBfnYxA.mp4",
            "path": "music_x1/videos/The Tear Of The Year ~ Jackie Wilson (1960)-ESX5rBfnYxA.mp4",
            "size": 5.057575936
        },
        {
            "name": "Calo - La Colegiala Feat. Margarita La Diosa de la Cumbia (Video Oficial)-hPKpedWsutY.mp4",
            "path": "music_x1/videos/Calo - La Colegiala Feat. Margarita La Diosa de la Cumbia (Video Oficial)-hPKpedWsutY.mp4",
            "size": 20.381952000000002
        },
        {
            "name": "Los Hermanos Vega El Estudiante-jpOKQGwmikY.mp4",
            "path": "music_x1/videos/Los Hermanos Vega El Estudiante-jpOKQGwmikY.mp4",
            "size": 6.146312192000001
        },
        {
            "name": "Cariño Inmenso-bEk6SRWEoJI.mp4",
            "path": "music_x1/videos/Cariño Inmenso-bEk6SRWEoJI.mp4",
            "size": 7.843728384
        },
        {
            "name": "The Difference Between Us-lIRbBRHU8H8.mp4",
            "path": "music_x1/videos/The Difference Between Us-lIRbBRHU8H8.mp4",
            "size": 5.7482762240000005
        },
        {
            "name": "Piperrak - Gora Sartaguda-tFR6TQApMck.mp4",
            "path": "music_x1/videos/Piperrak - Gora Sartaguda-tFR6TQApMck.mp4",
            "size": 5.842692096
        },
        {
            "name": "The Kagas - Vacaciones en Europa (Los Emigrantes)-8zKaotLPVj0.mp4",
            "path": "music_x1/videos/The Kagas - Vacaciones en Europa (Los Emigrantes)-8zKaotLPVj0.mp4",
            "size": 4.842788864
        },
        {
            "name": "Leoni Torres - Toda Una Vida (Video Oficial)-WOaVhrDLVzQ.mp4",
            "path": "music_x1/videos/Leoni Torres - Toda Una Vida (Video Oficial)-WOaVhrDLVzQ.mp4",
            "size": 14.221133824
        },
        {
            "name": "Carlos Vega Eslabon Por Eslabon-Dwjs110taLw.mp4",
            "path": "music_x1/videos/Carlos Vega Eslabon Por Eslabon-Dwjs110taLw.mp4",
            "size": 5.154409472
        },
        {
            "name": "These Foolish Things (Remind Me Of You)-aJZOUXtDCn0.mp4",
            "path": "music_x1/videos/These Foolish Things (Remind Me Of You)-aJZOUXtDCn0.mp4",
            "size": 12.70706176
        },
        {
            "name": "Control Machete - Te Aprovechas Del Limite-488ZvfNlkoc.mp4",
            "path": "music_x1/videos/Control Machete - Te Aprovechas Del Limite-488ZvfNlkoc.mp4",
            "size": 4.257348608
        },
        {
            "name": "El Pirulino-mjkD4E7mez4.mp4",
            "path": "music_x1/videos/El Pirulino-mjkD4E7mez4.mp4",
            "size": 6.160945152
        },
        {
            "name": "Por si volvieras - José Luis Rodríguez - El Puma-SnSGxAg06zM.mp4",
            "path": "music_x1/videos/Por si volvieras - José Luis Rodríguez - El Puma-SnSGxAg06zM.mp4",
            "size": 4.78032896
        },
        {
            "name": "La Arrolladora Banda El Limón De René Camacho - Como Perro Atropellado (Lyric Video)-xoxFAJVRQ3c.mp4",
            "path": "music_x1/videos/La Arrolladora Banda El Limón De René Camacho - Como Perro Atropellado (Lyric Video)-xoxFAJVRQ3c.mp4",
            "size": 4.798436352
        },
        {
            "name": "Piero - Dígame, Dígame [Canción Oficial] ®-4moAA_0YzZA.mp4",
            "path": "music_x1/videos/Piero - Dígame, Dígame [Canción Oficial] ®-4moAA_0YzZA.mp4",
            "size": 6.662478848
        },
        {
            "name": "Joan Sebastian - Me Gustas (Letra Oficial)-Fraqb7wyofE.mp4",
            "path": "music_x1/videos/Joan Sebastian - Me Gustas (Letra Oficial)-Fraqb7wyofE.mp4",
            "size": 9.36620544
        },
        {
            "name": "The Misfits - Last Caress-F39UP1mjAnc.mp4",
            "path": "music_x1/videos/The Misfits - Last Caress-F39UP1mjAnc.mp4",
            "size": 9.488293888000001
        },
        {
            "name": "Johnny Cash - Give My Love To Rose-D1LBKTONZ0M.mp4",
            "path": "music_x1/videos/Johnny Cash - Give My Love To Rose-D1LBKTONZ0M.mp4",
            "size": 3.5495096320000004
        },
        {
            "name": "The Residents - Tragic Bells-MDiT-lqY_Ww.mp4",
            "path": "music_x1/videos/The Residents - Tragic Bells-MDiT-lqY_Ww.mp4",
            "size": 5.865506816000001
        },
        {
            "name": "Edna ~ The Medallions (1955)(78 rpm)-v5BxZYlKDhY.mp4",
            "path": "music_x1/videos/Edna ~ The Medallions (1955)(78 rpm)-v5BxZYlKDhY.mp4",
            "size": 7.838823424
        },
        {
            "name": "Creedence Clearwater Revival - Ooby Dooby-vQGp83kAwUk.mp4",
            "path": "music_x1/videos/Creedence Clearwater Revival - Ooby Dooby-vQGp83kAwUk.mp4",
            "size": 5.735960576
        },
        {
            "name": "Tonino Carotone - Me Cago En El Amor [Official Music Video]-cu3K1njbYqs.mp4",
            "path": "music_x1/videos/Tonino Carotone - Me Cago En El Amor [Official Music Video]-cu3K1njbYqs.mp4",
            "size": 22.61512192
        },
        {
            "name": "09-Sarri Sarri - Kortatu-Z3QxJmetVgY.mp4",
            "path": "music_x1/videos/09-Sarri Sarri - Kortatu-Z3QxJmetVgY.mp4",
            "size": 6.175849472
        }
    ],
    "total_size": 973.4965923839999
}